protocals/__init__.py
protocals/mcp.py
openprotocal-0.1.0.dist-info/LICENSE
openprotocal-0.1.0.dist-info/METADATA
openprotocal-0.1.0.dist-info/WHEEL
openprotocal-0.1.0.dist-info/top_level.txt
openprotocal-0.1.0.dist-info/RECORD
